<?xml version="1.0" encoding="UTF-8"?>
<phpdoc xmlns="http://www.phpdoc.org/phpDocumentor/config"
        xmlns:xsi="http://www.w3.org/2001/XMLSchema-instance"
        xsi:noNamespaceSchemaLocation="https://docs.phpdoc.org/latest/phpdoc.xsd"
        version="3.0"
>
    <paths>
        <output>docs/api</output>
        <cache>.phpdoc/cache</cache>
    </paths>
    <version number="3.0.0">
        <api format="php">
            <source dsn=".">
                <path>src</path>
            </source>
            <output>api</output>
            <ignore hidden="true" symlinks="true">
                <path>vendor/**/*</path>
                <path>tests/**/*</path>
            </ignore>
            <extensions>
                <extension>php</extension>
            </extensions>
        </api>
    </version>
</phpdoc>
